ContactMechanics/ChangeLog.md
ContactMechanics/FFTElasticHalfSpace.py
ContactMechanics/Factory.py
ContactMechanics/PipelineFunction.py
ContactMechanics/PlasticSystemSpecialisations.py
ContactMechanics/Substrates.py
ContactMechanics/Systems.py
ContactMechanics/__init__.py
ContactMechanics/test_surface_topography.py
ContactMechanics/CommandLineInterface/HardWall.py
ContactMechanics/CommandLineInterface/__init__.py
ContactMechanics/GreensFunctions/Anisotropic.py
ContactMechanics/GreensFunctions/Isotropic.py
ContactMechanics/GreensFunctions/__init__.py
ContactMechanics/IO/NetCDF.py
ContactMechanics/IO/__init__.py
ContactMechanics/Optimization/ConstrainedConjugateGradients.py
ContactMechanics/Optimization/__init__.py
ContactMechanics/ReferenceSolutions/Cone.py
ContactMechanics/ReferenceSolutions/GreenwoodTripp.py
ContactMechanics/ReferenceSolutions/Hertz.py
ContactMechanics/ReferenceSolutions/Westergaard.py
ContactMechanics/ReferenceSolutions/__init__.py
ContactMechanics/Tools/Logger.py
ContactMechanics/Tools/__init__.py
ContactMechanics/Tools/common.py
contactmechanics-1.6.1.dist-info/entry_points.txt
contactmechanics-1.6.1.dist-info/licenses/LICENSE.md
contactmechanics-1.6.1.dist-info/WHEEL
contactmechanics-1.6.1.dist-info/METADATA
contactmechanics-1.6.1.dist-info/RECORD
