Metadata-Version: 2.4
Name: ContactMechanics
Version: 1.6.1
Summary: Efficient contact mechanics using elastic half-space methods
Author-email: Till Junge <till.junge@altermail.ch>, Lars Pastewka <lars.pastewka@imtek.uni-freiburg.de>, Antoine Sanner <antoine.sanner@ethz.ch>
Requires-Python: >=3.9.0
Classifier: Development Status :: 5 - Production/Stable
Classifier: Programming Language :: Python
License-File: LICENSE.md
Requires-Dist: DiscoverVersion
Requires-Dist: numpy
Requires-Dist: scipy>=1.9.0
Requires-Dist: NuMPI>=0.5.0
Requires-Dist: muFFT>=0.93.1
Requires-Dist: SurfaceTopography>=1.17.1
Requires-Dist: sphinx ; extra == "docs"
Requires-Dist: sphinx-rtd-theme ; extra == "docs"
Requires-Dist: myst_nb ; extra == "docs"
Requires-Dist: numpydoc ; extra == "docs"
Requires-Dist: flake8<8 ; extra == "test"
Requires-Dist: pytest ; extra == "test"
Requires-Dist: pytest-cov ; extra == "test"
Requires-Dist: pytest-flake8 ; extra == "test"
Requires-Dist: runtests ; extra == "test"
Project-URL: changelog, https://github.com/ContactEngineering/ContactMechanics/blob/master/ContactMechanics/ChangeLog.md
Project-URL: documentation, https://contactengineering.github.io/ContactMechanics/
Project-URL: repository, https://github.com/ContactEngineering/ContactMechanics
Provides-Extra: docs
Provides-Extra: test
